[
	{
		"id": 1,
		"title": "hyoka",
		"description": "A fast and precise math expression parser and evaluator for JavaScript and Typescript. Avalable on npm and can also be imported directly into browsers via CDNs",
		"tech": ["typescript"],
		"link": "https://www.npmjs.com/package/hyoka",
		"image": "/images/hyoka-5.png",
		"repolink": "https://github.com/olamide203/hyoka"
	},
	{
		"id": 2,
		"title": "gittz",
		"description": "A full-stack web app which consumes the Github API to display a user's profile and repositories and also allows users to search for other users. it also integrates with the twitter API allowing users to share their projects on twitter",
		"tech": ["react", "nodejs", "express"],
		"link": "https://www.gitsocial.net",
		"image": "https://www.gitsocial.net/images/meta.png",
		"repolink": "https://github.com/olamide203/gittz"
	}
]
